rufous_result/__init__.py
rufous_result/result.py
rufous_result-0.1.0.dist-info/LICENSE
rufous_result-0.1.0.dist-info/WHEEL
rufous_result-0.1.0.dist-info/METADATA
rufous_result-0.1.0.dist-info/RECORD
