Metadata-Version: 2.1
Name: rufous-result
Version: 0.1.0
Summary: Translation of Rust's Result type to Python 3.
License: MIT
Author: Gavriel Rachael-Homann
Author-email: gavriel@gavriel.dev
Requires-Python: >=3.7,<4.0
Classifier: License :: OSI Approved :: MIT License
Classifier: Programming Language :: Python :: 3
Classifier: Programming Language :: Python :: 3.10
Classifier: Programming Language :: Python :: 3.7
Classifier: Programming Language :: Python :: 3.8
Classifier: Programming Language :: Python :: 3.9
